[
    {
        "AQI": 23.28,
        "datetime": "2019-01-01",
        "trend": 1.22
    },
    {
        "AQI": 24.03,
        "datetime": "2019-01-02",
        "trend": 3.22
    },
    {
        "AQI": 24.58,
        "datetime": "2019-01-03",
        "trend": 2.29
    },
    {
        "AQI": 24.75,
        "datetime": "2019-01-04",
        "trend": 0.69
    },
    {
        "AQI": 24.95,
        "datetime": "2019-01-05",
        "trend": 0.81
    },
    {
        "AQI": 24.86,
        "datetime": "2019-01-06",
        "trend": -0.36
    },
    {
        "AQI": 25.74,
        "datetime": "2019-01-07",
        "trend": 3.54
    },
    {
        "AQI": 25.77,
        "datetime": "2019-01-08",
        "trend": 0.12
    },
    {
        "AQI": 25.47,
        "datetime": "2019-01-09",
        "trend": -1.16
    },
    {
        "AQI": 25.28,
        "datetime": "2019-01-10",
        "trend": -0.75
    }
]